pathurl/__init__.py
pathurl/_constants.py
pathurl/path.py
pathurl/py.typed
pathurl/query.py
pathurl/url.py
pathurl-0.8.0.dist-info/METADATA
pathurl-0.8.0.dist-info/WHEEL
pathurl-0.8.0.dist-info/RECORD
