Metadata-Version: 2.3
Name: pathurl
Version: 0.8.0
Summary: url manipulation
Home-page: https://pathurl.readthedocs.io/en/stable/
License: BSD-3-Clause
Keywords: url
Author: Stephanos Kuma
Author-email: "Stephanos Kuma" <stephanos@kuma.ai>
Requires-Python: >=3.9
Classifier: Development Status :: 4 - Beta
Classifier: Operating System :: OS Independent
Project-URL: Documentation, https://pathurl.readthedocs.io/en/stable/
Project-URL: Repository, https://github.com/spapanik/pathurl
